ndebug/__init__.py
ndebug/env_helpers.py
ndebug/lib.py
ndebug-0.1.1.dist-info/LICENSE
ndebug-0.1.1.dist-info/METADATA
ndebug-0.1.1.dist-info/WHEEL
ndebug-0.1.1.dist-info/top_level.txt
ndebug-0.1.1.dist-info/RECORD
