Metadata-Version: 2.1
Name: ndebug
Version: 0.1.1
Summary: Tiny python debugging utility like node.js debug module
Home-page: https://github.com/kmpm/py-ndebug
Author: Malcom Gilbert, Peter Magnusson
Author-email: peter@kmpm.se
License: MIT
Platform: UNKNOWN
Classifier: Programming Language :: Python
Classifier: Programming Language :: Python :: 3
Classifier: Programming Language :: Python :: 3.5
Requires-Dist: colorama (>=0.4.1)
